{
    "Image_3.JPG": [
        {
            "crop": "sapling_40.jpg",
            "angle": {
                "stalk_angle": 140.62,
                "tip_angle": 159.63
            }
        },
        {
            "crop": "sapling_41.jpg",
            "angle": {
                "stalk_angle": 146.73,
                "tip_angle": 107.46
            }
        },
        {
            "crop": "sapling_42.jpg",
            "angle": {
                "stalk_angle": 180.0,
                "tip_angle": 120.53
            }
        },
        {
            "crop": "sapling_54.jpg",
            "angle": {
                "stalk_angle": 144.46,
                "tip_angle": 149.33
            }
        },
        {
            "crop": "sapling_55.jpg",
            "angle": {
                "stalk_angle": 70.24,
                "tip_angle": 142.13
            }
        },
        {
            "crop": "sapling_58.jpg",
            "angle": {
                "stalk_angle": 71.86,
                "tip_angle": 153.21
            }
        }
    ]
}